__init__.py
planetaryconjunctions.py
separations.py
planetaryconjunctions-0.1.2.dist-info/LICENSE
planetaryconjunctions-0.1.2.dist-info/METADATA
planetaryconjunctions-0.1.2.dist-info/WHEEL
planetaryconjunctions-0.1.2.dist-info/top_level.txt
planetaryconjunctions-0.1.2.dist-info/RECORD
